[
    {
        "image": "../e.commerce.website/images/mixed/pottery.jpg",
        "title": "Shiny Pottery",
        "link": "../e.commerce.website/shop.html"
    },
    {
        "image": "../e.commerce.website/images/mixed/souvenir.jpg",
        "title": "Mixed Souvenirs",
        "link": "../e.commerce.website/shop.html"
    },
    {
        "image": "../e.commerce.website/images/mixed/candles.jpg",
        "title": "Cozy Candles",
        "link": "../e.commerce.website/shop.html"
    }
]
